xontrib/dracula.py
xontrib_dracula-0.1.1.dist-info/LICENSE
xontrib_dracula-0.1.1.dist-info/WHEEL
xontrib_dracula-0.1.1.dist-info/METADATA
xontrib_dracula-0.1.1.dist-info/RECORD
